hush/__init__.py
hush/_core.py
hush/py.typed
hush/plugin/__init__.py
hush/plugin/_core.py
hush/plugin/_hooks.py
hush/plugin/_specs.py
hush/plugin/_builtin/__init__.py
hush/plugin/_builtin/_core.py
hush/plugin/_builtin/envvars.py
hush/plugin/_builtin/pass_store.py
bolton_hush-0.1.0.dist-info/METADATA
bolton_hush-0.1.0.dist-info/WHEEL
bolton_hush-0.1.0.dist-info/top_level.txt
bolton_hush-0.1.0.dist-info/RECORD
