Metadata-Version: 2.1
Name: bolton-hush
Version: 0.1.0
Summary: A Python library that helps manage secrets using tools specified by plugin hooks.
Home-page: https://github.com/python-boltons/hush
Author: Bryan M Bugyi
Author-email: bryanbugyi34@gmail.com
License: MIT license
Platform: UNKNOWN
Classifier: Development Status :: 3 - Alpha
Classifier: Intended Audience :: Developers
Classifier: License :: OSI Approved :: MIT License
Classifier: Natural Language :: English
Classifier: Programming Language :: Python :: 3
Classifier: Programming Language :: Python :: 3.8
Classifier: Programming Language :: Python :: 3.9
Classifier: Programming Language :: Python :: 3.10
Requires-Python: >=3.8
Requires-Dist: bolton-eris (~=0.2.0)
Requires-Dist: bolton-proctor (~=0.2.0)
